.gitignore
readme.md
setup.py
upload_pypi.sh
onnxexplorer/common.py
onnxexplorer/core.py
onnxexplorer/msg.py
onnxexplorer/onnxexplorer.py
onnxexplorer/totrt.py
onnxexplorer/version.py
onnxexplorer.egg-info/PKG-INFO
onnxexplorer.egg-info/SOURCES.txt
onnxexplorer.egg-info/dependency_links.txt
onnxexplorer.egg-info/entry_points.txt
onnxexplorer.egg-info/requires.txt
onnxexplorer.egg-info/top_level.txt
onnxexplorer/__pycache__/core.cpython-35.pyc
onnxexplorer/__pycache__/core.cpython-36.pyc
onnxexplorer/__pycache__/core.cpython-38.pyc
onnxexplorer/__pycache__/onnxexplorer.cpython-35.pyc
onnxexplorer/__pycache__/onnxexplorer.cpython-36.pyc
onnxexplorer/__pycache__/onnxexplorer.cpython-38.pyc
onnxexplorer/proto/onnx-ml.proto
onnxexplorer/proto/onnx_ml_pb2.py
onnxexplorer/proto/__pycache__/onnx_ml_pb2.cpython-35.pyc
onnxexplorer/tests/test.py