Metadata-Version: 2.1
Name: onnxexplorer
Version: 0.2.5
Summary: Explorer for ONNX.
Home-page: https://github.com/jinfagang/onnxexplorer
Author: Lucas Jin
Author-email: jinfagang19@163.com
License: Apache 2.0
Keywords: deep learning,script helper,tools
Platform: any
